hid/__init__.py
hid-1.0.5.dist-info/LICENSE
hid-1.0.5.dist-info/METADATA
hid-1.0.5.dist-info/WHEEL
hid-1.0.5.dist-info/top_level.txt
hid-1.0.5.dist-info/RECORD
