Metadata-Version: 2.1
Name: hid
Version: 1.0.5
Summary: ctypes bindings for hidapi
Home-page: https://github.com/apmorton/pyhidapi
Author: Austin Morton
Author-email: amorton@juvsoft.com
License: MIT
Platform: UNKNOWN
Classifier: Intended Audience :: Developers
Classifier: License :: OSI Approved :: MIT License
Classifier: Operating System :: OS Independent
Classifier: Programming Language :: Python
Classifier: Programming Language :: Python :: 2.6
Classifier: Programming Language :: Python :: 2.7
Classifier: Programming Language :: Python :: 3
